README.md
setup.cfg
setup.py
whotrackme.egg-info/PKG-INFO
whotrackme.egg-info/SOURCES.txt
whotrackme.egg-info/dependency_links.txt
whotrackme.egg-info/entry_points.txt
whotrackme.egg-info/not-zip-safe
whotrackme.egg-info/requires.txt
whotrackme.egg-info/top_level.txt
whotracksme/__init__.py
whotracksme/main.py
whotracksme/data/__init__.py
whotracksme/data/loader.py
whotracksme/data/assets/__init__.py
whotracksme/website/__init__.py
whotracksme/website/builder.py
whotracksme/website/serve.py
whotracksme/website/templates.py
whotracksme/website/utils.py
whotracksme/website/build/__init__.py
whotracksme/website/build/blog.py
whotracksme/website/build/companies.py
whotracksme/website/build/home.py
whotracksme/website/build/trackers.py
whotracksme/website/build/websites.py
whotracksme/website/plotting/__init__.py
whotracksme/website/plotting/colors.py
whotracksme/website/plotting/companies.py
whotracksme/website/plotting/plots.py
whotracksme/website/plotting/sankey.py
whotracksme/website/plotting/trackers.py
whotracksme/website/plotting/utils.py