Metadata-Version: 1.1
Name: whotrackme
Version: 2017.11
Summary: Learn about tracking technologies, market structure and data-sharing on the web
Home-page: https://whotracks.me
Author: Cliqz Gmbh
Author-email: privacy@cliqz.com
License: MIT
Keywords: tracking whotracksme whotracks.me
Platform: UNKNOWN
Classifier: Development Status :: 4 - Beta
Classifier: Environment :: Console
Classifier: Intended Audience :: Developers
Classifier: Intended Audience :: Information Technology
Classifier: Intended Audience :: Science/Research
Classifier: License :: OSI Approved :: MIT License
Classifier: Operating System :: OS Independent
Classifier: Programming Language :: Python :: 3.6
Classifier: Topic :: Internet
Classifier: Topic :: Scientific/Engineering :: Information Analysis
